sentimod/__init__.py
sentimod/sentiment.py
sentimod/data/__init__.py
sentimod/data/_google.py
sentimod/data/_twitter.py
sentimod/data/_utils.py
sentimod/models/__init__.py
sentimod/models/_huggingface.py
sentimod/models/_polarity.py
sentimod/models/_subjectivity.py
sentimod/preprocessing/__init__.py
sentimod/preprocessing/_twitter.py
sentimod-0.0.2.dist-info/LICENSE
sentimod-0.0.2.dist-info/METADATA
sentimod-0.0.2.dist-info/WHEEL
sentimod-0.0.2.dist-info/top_level.txt
sentimod-0.0.2.dist-info/RECORD
