Metadata-Version: 2.1
Name: sentimod
Version: 0.0.2
Summary: small sentiment analysis package
Home-page: https://github.com/Dr-Entezari-s-Lab/sentimod.git
Author: Hamid Moradi
Author-email: Hamid Moradi <hordimad21@gmail.com>
Classifier: Programming Language :: Python :: 3
Classifier: License :: OSI Approved :: MIT License
Classifier: Operating System :: OS Independent
Requires-Python: >=3.8
License-File: LICENSE
Requires-Dist: requests
Requires-Dist: pandas
Requires-Dist: google-search-results
Requires-Dist: snscrape
Requires-Dist: tweet-preprocessor
Requires-Dist: matplotlib
Requires-Dist: numpy
